example_package_bd/main.py
example_package_bd-0.0.1.dist-info/METADATA
example_package_bd-0.0.1.dist-info/WHEEL
example_package_bd-0.0.1.dist-info/top_level.txt
example_package_bd-0.0.1.dist-info/RECORD
